odoo/addons/account_edi_ubl_cii_supplier_invoice_number/README.rst
odoo/addons/account_edi_ubl_cii_supplier_invoice_number/__init__.py
odoo/addons/account_edi_ubl_cii_supplier_invoice_number/__manifest__.py
odoo/addons/account_edi_ubl_cii_supplier_invoice_number/i18n/account_edi_ubl_cii_supplier_invoice_number.pot
odoo/addons/account_edi_ubl_cii_supplier_invoice_number/i18n/it.po
odoo/addons/account_edi_ubl_cii_supplier_invoice_number/models/__init__.py
odoo/addons/account_edi_ubl_cii_supplier_invoice_number/models/account_edi_xml_ubl_20.py
odoo/addons/account_edi_ubl_cii_supplier_invoice_number/readme/CONTRIBUTORS.rst
odoo/addons/account_edi_ubl_cii_supplier_invoice_number/readme/DESCRIPTION.rst
odoo/addons/account_edi_ubl_cii_supplier_invoice_number/readme/USAGE.rst
odoo/addons/account_edi_ubl_cii_supplier_invoice_number/static/description/icon.png
odoo/addons/account_edi_ubl_cii_supplier_invoice_number/static/description/index.html
odoo/addons/account_edi_ubl_cii_supplier_invoice_number/tests/__init__.py
odoo/addons/account_edi_ubl_cii_supplier_invoice_number/tests/test_alc_account_edi_ubl_cii_supplier_invoice_number.py
odoo_addon_account_edi_ubl_cii_supplier_invoice_number-16.0.1.0.0.4.dist-info/METADATA
odoo_addon_account_edi_ubl_cii_supplier_invoice_number-16.0.1.0.0.4.dist-info/WHEEL
odoo_addon_account_edi_ubl_cii_supplier_invoice_number-16.0.1.0.0.4.dist-info/top_level.txt
odoo_addon_account_edi_ubl_cii_supplier_invoice_number-16.0.1.0.0.4.dist-info/RECORD
