Metadata-Version: 2.1
Name: odoo-addon-account_edi_ubl_cii_supplier_invoice_number
Version: 16.0.1.0.0.4
Summary: This addon extends the UBL invoice import process to automatically populate the suppliers invoice number based on the value found in the XML file.
Home-page: https://github.com/OCA/edi
Author: Acsone SA/NV, Odoo Community Association (OCA)
Author-email: support@odoo-community.org
License: AGPL-3
Classifier: Programming Language :: Python
Classifier: Framework :: Odoo
Classifier: Framework :: Odoo :: 16.0
Classifier: License :: OSI Approved :: GNU Affero General Public License v3
Requires-Python: >=3.10
Requires-Dist: odoo-addon-account-invoice-supplier-ref-unique<16.1dev,>=16.0dev
Requires-Dist: odoo<16.1dev,>=16.0a
